calculator/tool.py
ankur8289_calculator-0.1.dist-info/METADATA
ankur8289_calculator-0.1.dist-info/WHEEL
ankur8289_calculator-0.1.dist-info/entry_points.txt
ankur8289_calculator-0.1.dist-info/top_level.txt
ankur8289_calculator-0.1.dist-info/RECORD
