Metadata-Version: 2.4
Name: ankur8289-calculator
Version: 0.1
Summary: A command line tool that accepts parameters
Requires-Python: >=3.8
